Metadata-Version: 2.1
Name: SDA-prim-package
Version: 4.3.0
Summary: A package that prints PRIM numbers
Home-page: UNKNOWN
Author: Guido Xhindoli
Author-email: <mail@gmail.com>
License: UNKNOWN
Keywords: pythonsdaal,SDA_prim_package,prim,prim  numbers,sda,SDA
Platform: UNKNOWN
Classifier: Development Status :: 1 - Planning
Classifier: Intended Audience :: Developers
Classifier: Programming Language :: Python :: 3
Classifier: Operating System :: Unix
Classifier: Operating System :: MacOS :: MacOS X
Classifier: Operating System :: Microsoft :: Windows
